time_decode/__init__.py
time_decode/time_decode.py
time_decode-10.3.1.dist-info/licenses/LICENSE
time_decode-10.3.1.dist-info/METADATA
time_decode-10.3.1.dist-info/WHEEL
time_decode-10.3.1.dist-info/entry_points.txt
time_decode-10.3.1.dist-info/top_level.txt
time_decode-10.3.1.dist-info/RECORD
