Metadata-Version: 2.4
Name: time-decode
Version: 10.3.1
Summary: Python 3 timestamp decode/encode tool
Author-email: "Corey Forman (digitalsleuth)" <github@digitalsleuth.ca>
Maintainer-email: "Corey Forman (digitalsleuth)" <github@digitalsleuth.ca>
Project-URL: Homepage, https://github.com/digitalsleuth/time_decode
Project-URL: References, https://github.com/digitalsleuth/time_decode/blob/master/REFERENCES.md
Keywords: digital forensics,dfir,timestamp,decode,encode
Classifier: Development Status :: 5 - Production/Stable
Classifier: Programming Language :: Python :: 3
Classifier: Operating System :: OS Independent
Requires-Python: >=3.9
License-File: LICENSE
Requires-Dist: PyQt6
Requires-Dist: colorama
Requires-Dist: tzdata
Requires-Dist: juliandate
Requires-Dist: prettytable
Requires-Dist: python-ulid>=3.1.0
Requires-Dist: bbpb
Dynamic: license-file
